kv_audio_pipeline/__init__.py
kv_audio_pipeline/audio_pipeline.py
kv_audio_pipeline-0.1.0.dist-info/METADATA
kv_audio_pipeline-0.1.0.dist-info/WHEEL
kv_audio_pipeline-0.1.0.dist-info/top_level.txt
kv_audio_pipeline-0.1.0.dist-info/RECORD
