Metadata-Version: 2.1
Name: kv-audio-pipeline
Version: 0.1.0
Author-email: Justin Bui <jmbui@klangverso.com>
Requires-Python: >=3.8
Requires-Dist: kv-text-to-speech
Requires-Dist: kv-text-processing
